{"name":"Daihatsu","slug":"daihatsu","letter":"d","items":[{"name":"Altis","slug":"altis","image":"_daihatsu-altis-altis-0.jpg"},{"name":"Applause","slug":"applause","image":"_daihatsu-applause-applause-ii-0.jpg"},{"name":"Atrai/extol","slug":"atraiextol","image":"_daihatsu-atrai-extol-atrai-extol-0.jpg"},{"name":"Ayla","slug":"ayla","image":"_daihatsu-ayla-ayla-facelift-2020-0.jpg"},{"name":"Be-go","slug":"be-go","image":"_daihatsu-be-go-be-go-cx-j-0.jpg"},{"name":"Boon","slug":"boon","image":"_daihatsu-boon-boon-0.jpg"},{"name":"Ceria","slug":"ceria","image":"_daihatsu-ceria-ceria-perodua-kancil-kelisa-0.jpg"},{"name":"Charade","slug":"charade","image":"_daihatsu-charade-charade-iv-com-g200-0.jpg"},{"name":"Charmant","slug":"charmant","image":"_daihatsu-charmant-charmant-a-0.jpg"},{"name":"Copen","slug":"copen","image":"_daihatsu-copen-copen-l8-0.jpg"},{"name":"Cuore","slug":"cuore","image":"_daihatsu-cuore-cuore-vii-l2-0.jpg"},{"name":"Delta","slug":"delta","image":"_daihatsu-delta-delta-wagon-0.jpg"},{"name":"Esse","slug":"esse","image":"_daihatsu-esse-esse-j-0.jpg"},{"name":"Feroza","slug":"feroza","image":"_daihatsu-feroza-feroza-hard-top-f300-0.jpg"},{"name":"Leeza","slug":"leeza","image":"_daihatsu-leeza-leeza-spider-0.jpg"},{"name":"Materia","slug":"materia","image":"_daihatsu-materia-materia-0.jpg"},{"name":"MAX","slug":"max","image":"_daihatsu-max-max-0.jpg"},{"name":"Mira","slug":"mira","image":"_daihatsu-mira-mira-gl800-0.jpg"},{"name":"Mira Gino","slug":"mira-gino","image":"_daihatsu-mira-gino-mira-gino-ii-0.jpg"},{"name":"Move","slug":"move","image":"_daihatsu-move-move-latte-l55-0.jpg"},{"name":"Naked","slug":"naked","image":"_daihatsu-naked-naked-0.jpg"},{"name":"Opti","slug":"opti","image":"_daihatsu-opti-opti-l8-0.jpg"},{"name":"Perodua Viva","slug":"perodua-viva","image":"_daihatsu-perodua-viva-perodua-viva-0.jpg"},{"name":"Pyzar","slug":"pyzar","image":"_daihatsu-pyzar-pyzar-g3-0.jpg"},{"name":"Rocky","slug":"rocky","image":"_daihatsu-rocky-rocky-a200-0.jpg"},{"name":"Sigra","slug":"sigra","image":"_daihatsu-sigra-sigra-facelift-2019-0.jpg"},{"name":"Sirion","slug":"sirion","image":"_daihatsu-sirion-sirion-m2-0.jpg"},{"name":"Sonica","slug":"sonica","image":"_daihatsu-sonica-sonica-0.jpg"},{"name":"Storia","slug":"storia","image":"_daihatsu-storia-storia-m1-0.jpg"},{"name":"Tanto","slug":"tanto","image":"_daihatsu-tanto-tanto-0.jpg"},{"name":"Terios","slug":"terios","image":"_daihatsu-terios-terios-iii-j300-0.jpg"},{"name":"Trevis","slug":"trevis","image":"_daihatsu-trevis-trevis-0.jpg"},{"name":"Wildcat/rocky","slug":"wildcatrocky","image":"carpicture.jpg"},{"name":"Xenia","slug":"xenia","image":"_daihatsu-xenia-xenia-iii-0.jpg"},{"name":"YRV","slug":"yrv","image":"_daihatsu-yrv-yrv-0.jpg"}]}