{"name":"Moskvich","slug":"moskvich","letter":"m","items":[{"name":"2136 Kombi","slug":"2136-kombi","image":"carpicture.jpg"},{"name":"2137 Kombi","slug":"2137-kombi","image":"_moskvich-2137-kombi-2137-combi-0.jpg"},{"name":"2138","slug":"2138","image":"carpicture.jpg"},{"name":"2140","slug":"2140","image":"_moskvich-2140-2140-0.jpg"},{"name":"2141","slug":"2141","image":"carpicture.jpg"},{"name":"400","slug":"400","image":"carpicture.jpg"},{"name":"401","slug":"401","image":"carpicture.jpg"},{"name":"402","slug":"402","image":"carpicture.jpg"},{"name":"403","slug":"403","image":"carpicture.jpg"},{"name":"407","slug":"407","image":"carpicture.jpg"},{"name":"408","slug":"408","image":"_moskvich-408-408-0.jpg"},{"name":"412","slug":"412","image":"_moskvich-412-412-ie-0.jpg"},{"name":"423 Kombi","slug":"423-kombi","image":"_moskvich-423-kombi-423-combi-0.jpg"},{"name":"427","slug":"427","image":"_moskvich-427-427-0.jpg"},{"name":"434","slug":"434","image":"_moskvich-434-434-0.jpg"},{"name":"Knyaz Vladimir","slug":"knyaz-vladimir","image":"carpicture.jpg"},{"name":"Yuriy Dolgorukiy","slug":"yuriy-dolgorukiy","image":"carpicture.jpg"}]}