{"name":"Кари","hideprice":true,"fields":[{"name":"brand","placeholder":"Марка","type":"text","required":true},{"name":"condition","placeholder":"Състояние","type":"radio","options":["Нов","Употребяван","На части"],"required":true},{"name":"type","placeholder":"Тип","type":"radio","options":["Електрокар","Мотокар - бензинов","Мотокар - дизелов","Газокар","Друг"],"required":true},{"name":"year","placeholder":"Година производство","type":"number","required":true,"after":"год."},{"name":"optional","placeholder":"Особености","type":"checkbox","options":["Бартер","Застраховка","Лизинг","Нов внос","Климатик"]},{"name":"priceimoti","type":"component","placeholder":"component","required":true}],"slug":"R64i","parrent":"kHUm"}